bammm/__init__.py
bammm/bammm.py
bammm_ozika-0.0.8.dist-info/LICENSE
bammm_ozika-0.0.8.dist-info/METADATA
bammm_ozika-0.0.8.dist-info/WHEEL
bammm_ozika-0.0.8.dist-info/top_level.txt
bammm_ozika-0.0.8.dist-info/RECORD
