Metadata-Version: 2.1
Name: bammm-ozika
Version: 0.0.8
Summary: Bayesian model management
Author-email: Ondrej Zika <author@example.com>
License: Copyright (c) 2018 The Python Packaging Authority        
Project-URL: Homepage, https://github.com/ozika/bammm
Project-URL: Bug Tracker, https://github.com/ozika/bammm/issues
Classifier: Programming Language :: Python :: 3
Classifier: License :: OSI Approved :: MIT License
Classifier: Operating System :: OS Independent
Requires-Python: >=3.7
License-File: LICENSE
Requires-Dist: pickle-mixin (>=1.0.0)
Requires-Dist: bambi (>=0.8.0)
